{"_id":{"$oid":"5727eceef4f55c3f2c2d62b1"},"age":200,"species":"sequoia","__v":0}
{"_id":{"$oid":"5727f171372a41622c7c2d90"},"age":200,"species":"sequoia","__v":0}
{"_id":{"$oid":"5727f173372a41622c7c2d91"},"age":200,"species":"sequoia","__v":0}
{"_id":{"$oid":"5727f174372a41622c7c2d92"},"age":200,"species":"sequoia","__v":0}
{"_id":{"$oid":"5727f174372a41622c7c2d93"},"age":200,"species":"sequoia","__v":0}
{"_id":{"$oid":"5727f175372a41622c7c2d94"},"age":200,"species":"sequoia","__v":0}
{"_id":{"$oid":"5728fbecf579d22639957bfb"},"age":1,"species":"bush","createdAt":{"$date":"2016-05-03T19:28:44.361Z"},"__v":13,"creatures":[null,null,null,null,null,null,null,"dddd","dddd",null,null,"thingy","something_else"]}
{"_id":{"$oid":"5729087df560e37f39037bdc"},"age":1,"createdAt":{"$date":"2016-05-03T20:22:21.850Z"},"species":"bush","__v":0}
{"_id":{"$oid":"572908cf2db6ac89392912a3"},"age":1,"createdAt":{"$date":"2016-05-03T20:23:43.295Z"},"species":"popular","__v":0}
{"_id":{"$oid":"572908d02db6ac89392912a4"},"age":1,"createdAt":{"$date":"2016-05-03T20:23:44.694Z"},"species":"popular","__v":0}
{"_id":{"$oid":"572908d772417a93398996f1"},"age":1,"createdAt":{"$date":"2016-05-03T20:23:51.038Z"},"species":"popular","__v":0}
{"_id":{"$oid":"572908d772417a93398996f2"},"age":1,"createdAt":{"$date":"2016-05-03T20:23:51.653Z"},"species":"popular","__v":0}
{"_id":{"$oid":"572908d772417a93398996f3"},"age":1,"createdAt":{"$date":"2016-05-03T20:23:51.916Z"},"species":"popular","__v":0}
{"_id":{"$oid":"572908d872417a93398996f4"},"age":1,"createdAt":{"$date":"2016-05-03T20:23:52.085Z"},"species":"popular","__v":0}
{"_id":{"$oid":"572908d872417a93398996f5"},"age":1,"createdAt":{"$date":"2016-05-03T20:23:52.229Z"},"species":"popular","__v":0}
{"_id":{"$oid":"572908d872417a93398996f6"},"age":1,"createdAt":{"$date":"2016-05-03T20:23:52.434Z"},"species":"popular","__v":0}
{"_id":{"$oid":"572908eee397679739cdde67"},"age":1,"createdAt":{"$date":"2016-05-03T20:24:14.866Z"},"species":"popular","__v":0}
{"_id":{"$oid":"572908efe397679739cdde68"},"age":1,"createdAt":{"$date":"2016-05-03T20:24:15.574Z"},"species":"popular","__v":0}
{"_id":{"$oid":"572908fde397679739cdde69"},"age":1,"createdAt":{"$date":"2016-05-03T20:24:29.876Z"},"species":"popular","__v":0}
{"_id":{"$oid":"572908fee397679739cdde6a"},"age":1,"createdAt":{"$date":"2016-05-03T20:24:30.526Z"},"species":"popular","__v":0}
{"_id":{"$oid":"572908ffe397679739cdde6b"},"age":1,"createdAt":{"$date":"2016-05-03T20:24:31.084Z"},"species":"popular","__v":0}
{"_id":{"$oid":"572908ffe397679739cdde6c"},"age":1,"createdAt":{"$date":"2016-05-03T20:24:31.454Z"},"species":"popular","__v":0}
{"_id":{"$oid":"572908ffe397679739cdde6d"},"age":1,"createdAt":{"$date":"2016-05-03T20:24:31.637Z"},"species":"popular","__v":0}
{"_id":{"$oid":"572908ffe397679739cdde6e"},"age":1,"createdAt":{"$date":"2016-05-03T20:24:31.789Z"},"species":"popular","__v":0}
{"_id":{"$oid":"572908ffe397679739cdde6f"},"age":1,"createdAt":{"$date":"2016-05-03T20:24:31.980Z"},"species":"popular","__v":0}
{"_id":{"$oid":"5729090f0979c1a5393a82f1"},"age":1,"createdAt":{"$date":"2016-05-03T20:24:47.330Z"},"species":"popular","__v":0}
{"_id":{"$oid":"572909100979c1a5393a82f2"},"age":1,"createdAt":{"$date":"2016-05-03T20:24:48.128Z"},"species":"popular","__v":0}
{"_id":{"$oid":"57290949379396af39e58516"},"age":1,"createdAt":{"$date":"2016-05-03T20:25:45.041Z"},"species":"popular","__v":0}
{"_id":{"$oid":"57290949379396af39e58517"},"age":1,"createdAt":{"$date":"2016-05-03T20:25:45.699Z"},"species":"popular","__v":0}
{"_id":{"$oid":"5729094a379396af39e58518"},"age":1,"createdAt":{"$date":"2016-05-03T20:25:46.210Z"},"species":"popular","__v":0}
{"_id":{"$oid":"57290a6afeebe8c43972c778"},"age":1,"species":"pine","createdAt":{"$date":"2016-05-03T20:30:34.459Z"},"__v":0}
{"_id":{"$oid":"57290acff38933d539c259dd"},"age":1,"species":"pine","creatures":[],"createdAt":{"$date":"2016-05-03T20:32:15.515Z"},"__v":0}
{"_id":{"$oid":"57290ad1f38933d539c259de"},"age":1,"species":"pine","creatures":[],"createdAt":{"$date":"2016-05-03T20:32:17.154Z"},"__v":0}
{"_id":{"$oid":"57290ae9699432d93971f7ff"},"age":1,"species":"pine","creatures":[],"createdAt":{"$date":"2016-05-03T20:32:41.051Z"},"__v":0}
{"_id":{"$oid":"572913ec1d295f603a2ad7a9"},"age":1,"species":"pine","creatures":[],"createdAt":{"$date":"2016-05-03T21:11:08.436Z"},"__v":0}
